[
  {
    "slug": "octantes",
    "title": "octantes",
    "description": "",
    "type": "note",
    "tags": [],
    "portada": "",
    "handle": "kaste",
    "date": "12/10/2025",
    "isoDate": "2025-10-12T03:01:43.134Z",
    "url": "/posts/note/octantes/"
  },
  {
    "slug": "octantes",
    "title": "octantes",
    "description": "",
    "type": "music",
    "tags": [],
    "portada": "",
    "handle": "kaste",
    "date": "12/10/2025",
    "isoDate": "2025-10-12T03:01:43.132Z",
    "url": "/posts/music/octantes/"
  },
  {
    "slug": "musica",
    "title": "musica",
    "description": "",
    "type": "music",
    "tags": [],
    "portada": "https://octantes.github.io/posts/music/musica/portal.webp",
    "handle": "kaste",
    "date": "12/10/2025",
    "isoDate": "2025-10-12T03:01:43.130Z",
    "url": "/posts/music/musica/"
  },
  {
    "slug": "octantes",
    "title": "octantes",
    "description": "",
    "type": "dev",
    "tags": [],
    "portada": "",
    "handle": "kaste",
    "date": "12/10/2025",
    "isoDate": "2025-10-12T03:01:40.571Z",
    "url": "/posts/dev/octantes/"
  },
  {
    "slug": "dinamik",
    "title": "dinamik - branding",
    "description": "descripcion corta para seo",
    "type": "design",
    "tags": [
      "branding",
      "portfolio"
    ],
    "portada": "",
    "handle": "kaste",
    "date": "30/11/2024",
    "isoDate": "2024-11-30T00:00:00.000Z",
    "url": "/posts/design/dinamik/"
  },
  {
    "slug": "cruzar",
    "title": "cruzar - cordillera cripto",
    "description": "descripcion corta para seo",
    "type": "design",
    "tags": [
      "branding",
      "portfolio"
    ],
    "portada": "",
    "handle": "kaste",
    "date": "19/09/2024",
    "isoDate": "2024-09-19T00:00:00.000Z",
    "url": "/posts/design/cruzar/"
  },
  {
    "slug": "enuna",
    "title": "en una - branding",
    "description": "descripcion corta para seo",
    "type": "design",
    "tags": [
      "branding",
      "portfolio"
    ],
    "portada": "",
    "handle": "kaste",
    "date": "06/09/2023",
    "isoDate": "2023-09-06T00:00:00.000Z",
    "url": "/posts/design/enuna/"
  }
]